test/__init__.py
test/test_transformation.py
truncatedgaussianmixtures/__init__.py
truncatedgaussianmixtures/annealing_schedule.py
truncatedgaussianmixtures/conversions.py
truncatedgaussianmixtures/fit_gmm.py
truncatedgaussianmixtures/fit_kde.py
truncatedgaussianmixtures/gmm.py
truncatedgaussianmixtures/julia_extensions.py
truncatedgaussianmixtures/julia_helpers.py
truncatedgaussianmixtures/julia_import.py
truncatedgaussianmixtures/kde.py
truncatedgaussianmixtures/transformations.py
truncatedgaussianmixtures-0.1.7.dist-info/METADATA
truncatedgaussianmixtures-0.1.7.dist-info/WHEEL
truncatedgaussianmixtures-0.1.7.dist-info/top_level.txt
truncatedgaussianmixtures-0.1.7.dist-info/RECORD
